hms/__init__.py
hms/abcc40/__init__.py
hms_abcc40-0.0.1.dist-info/LICENSE
hms_abcc40-0.0.1.dist-info/METADATA
hms_abcc40-0.0.1.dist-info/WHEEL
hms_abcc40-0.0.1.dist-info/top_level.txt
hms_abcc40-0.0.1.dist-info/RECORD
