Metadata-Version: 2.1
Name: hms-abcc40
Version: 0.0.1
Summary: Anybus CompactCom40 access via REST
Home-page: https://github.com/hms-networks/hms-abcc40
Author: HMS Industrial Networks AB
Author-email: pythoncontact@hms.se
License: UNKNOWN
Platform: UNKNOWN
Classifier: Development Status :: 3 - Alpha
Classifier: License :: OSI Approved :: Apache Software License
Classifier: Programming Language :: Python :: 2.7
Classifier: Programming Language :: Python :: 3.5
Classifier: Programming Language :: Python :: 3.6
Classifier: Programming Language :: Python :: 3.7
Classifier: Operating System :: OS Independent
